asyncev/__init__.py
asyncev/asyncev.py
asyncev/py.typed
asyncev-1.0.1.dist-info/METADATA
asyncev-1.0.1.dist-info/WHEEL
asyncev-1.0.1.dist-info/licenses/LICENSE
asyncev-1.0.1.dist-info/RECORD
