Metadata-Version: 2.4
Name: asyncev
Version: 1.0.1
Summary: Asynchronous named events with no dependencies
Project-URL: Homepage, https://github.com/acetylen/asyncev
Project-URL: Issues, https://github.com/acetylen/asyncev/issues
Author: Emil Tylén
License-Expression: MIT
License-File: LICENSE
Keywords: async,asyncio,event,library
Classifier: Development Status :: 5 - Production/Stable
Classifier: Intended Audience :: Developers
Classifier: License :: OSI Approved :: MIT License
Classifier: Operating System :: OS Independent
Classifier: Programming Language :: Python :: 3
Classifier: Programming Language :: Python :: 3.9
Classifier: Programming Language :: Python :: 3.10
Classifier: Programming Language :: Python :: 3.11
Classifier: Programming Language :: Python :: 3.12
Classifier: Programming Language :: Python :: 3.13
Classifier: Programming Language :: Python :: 3.14
Classifier: Topic :: Software Development :: Libraries
Classifier: Typing :: Typed
Requires-Python: >=3.9
